graphql_response_validator/__init__.py
graphql_response_validator-0.0.1.dist-info/LICENSE
graphql_response_validator-0.0.1.dist-info/WHEEL
graphql_response_validator-0.0.1.dist-info/METADATA
graphql_response_validator-0.0.1.dist-info/RECORD
